Workbook

Sheet Read Me
A1: RHTP Modular Implementation & Cost Model
A2: Companion workbook to “RHTP Modular Implementation & Cost Strategy” | Prepared by Rick Williams, IBM RHTP Team | July 2026
A4: Purpose and scope
A5: This workbook models the cost to build and run RHTP as a modular platform, sized against a single
A6: illustrative reference deployment: one state Medicaid MCO / county program, roughly 300,000 covered lives,
A7: phased from a single-cohort pilot to statewide scale. Every dollar figure, rate, and effort estimate is a
A8: placeholder for your team to replace with real IBM rate-card figures and actual client scope — the value of
A9: this workbook is the structure (modules, phasing, formulas), not the specific numbers.
A11: How the sheets fit together
A12: Rate Card — Illustrative onshore vs. offshore blended hourly rates by role. Replace with the real IBM rate card.
A13: Assumptions — Global levers: hours per FTE-month, blended company rates, and default onshore/offshore mix by module type.
A14: Module Build Cost — All 23 build modules (core platform, persona experiences, data connectors) with effort (FTE-months), onshore/offshore mix, and computed build cost.
... A26: All figures are illustrative placeholders prepared for internal strategy discussion. Validate with IBM Consulting's actual rate card, delivery estimating standards, and the target client's real population and contract scope before external use.

Sheet Rate Card
A1: Illustrative Role Rate Card (Loaded Hourly, USD)
A2: Placeholder rates — replace with the current IBM Consulting rate card for the engaged geography and labor category.
A4: Role | B4: Onshore Rate ($/hr) | C4: Offshore Rate ($/hr) | D4: Notes
A5: Engagement / Program Lead | B5: 220 | C5: 70 | D5: Overall delivery lead; typically onshore-heavy
A6: Solution Architect (FHIR / Knowledge Graph) | B6: 245 | C6: 85 | D6: Core platform architecture
A7: AI / Agent Orchestration Engineer | B7: 210 | C7: 75 | D7: Builds and tunes the agent orchestration layer
A8: Data / Integration Engineer | B8: 185 | C8: 60 | D8: Connectors, ETL, FHIR Bulk Data pipelines
A9: Platform / DevSecOps Engineer | B9: 190 | C9: 65 | D9: Hosting, CI/CD, observability, security controls
A10: UX / Product Designer | B10: 165 | C10: 55 | D10: Persona-specific experience design
A11: QA / Test Engineer | B11: 150 | C11: 45 | D11: Functional, integration, and regression testing
A12: Clinical / Business SME | B12: 200 | C12: n/a | D12: Care management & SDOH subject-matter input; typically onshore only
A13: Change Management / Training | B13: 160 | C13: 50 | D13: End-user adoption, training materials, rollout support
A14: Support Analyst (L1/L2) | B14: 130 | C14: 40 | D14: Steady-state helpdesk and monitoring

Sheet Assumptions
A1: Global Assumptions
A2: Levers used throughout the Module Build Cost, Phase Summary, and Run & Maintain sheets.
A4: Assumption | B4: Value | C4: Note
A5: Hours per FTE-month | B5: 160 | C5: Standard full-time monthly billable hours
A6: Months per year | B6: 12
A8: Company blended rates (used for module-level build costing)
A9: Blended onshore rate ($/hr) | B9: 195 | C9: Approximate team-weighted average across Rate Card roles; refine once the Phase 1 team roster is set
A10: Blended offshore rate ($/hr) | B10: 65
A12: Default onshore mix by module type (editable per-row in Module Build Cost)
A13: Core Platform modules — % onshore | B13: 0.65 | C13: Architecture-heavy; more senior, onshore-weighted
A14: Persona Module modules — % onshore | B14: 0.45
A15: Data Connector modules — % onshore | B15: 0.35 | C15: Integration engineering can be leveraged more heavily offshore
A17: AI-assisted (Bob/Claude) build acceleration by module type
A18: Core Platform modules — Bob hours as % of dev-team hours | B18: 0.5 | C18: Architecture-, security-, and compliance-heavy; human review/validation remains the bottleneck even with AI-assisted coding
A19: Persona Module modules — Bob hours as % of dev-team hours | B19: 0.3 | C19: UI/workflow-heavy screens; AI pair-development accelerates scaffolding, forms, and CRUD logic significantly
A20: Data Connector modules — Bob hours as % of dev-team hours | B20: 0.35 | C20: Mapping/ETL code generates quickly with AI; hours remain bounded by testing against real source systems

Sheet Module Build Cost
A1: Module Build Cost — All Phases
A2: Effort (FTE-months) and onshore/offshore mix are inputs; hours and cost columns are formulas. Sized against the reference 300K-covered-lives deployment.
A5: # | B5: Module | C5: Category | D5: Phase | E5: FTE-Months | F5: % Onshore | G5: % Offshore | H5: Onshore Hrs | I5: Offshore Hrs | J5: Onshore Cost | K5: Offshore Cost | L5: Total Build Cost
A6: 1 | B6: C1. FHIR-Native Integration & Ingestion Layer (real-time API gateway + batch ETL / Bulk Data) | C6: Core Platform | D6: 1 | E6: 8 | F6: =Assumptions!$B$13 -> 0.65 | G6: =1-F6 -> 0.35 | H6: =$E6*Assumptions!$B$5*F6 -> 832 | I6: =$E6*Assumptions!$B$5*G6 -> 448 | J6: =H6*Assumptions!$B$9 -> 162240 | K6: =I6*Assumptions!$B$10 -> 29120 | L6: =J6+K6 -> 191360
A7: 2 | B7: C2. Knowledge Graph & Master Person Index | C7: Core Platform | D7: 1 | E7: 6 | F7: =Assumptions!$B$13 -> 0.65 | G7: =1-F7 -> 0.35 | H7: =$E7*Assumptions!$B$5*F7 -> 624 | I7: =$E7*Assumptions!$B$5*G7 -> 336 | J7: =H7*Assumptions!$B$9 -> 121680 | K7: =I7*Assumptions!$B$10 -> 21840 | L7: =J7+K7 -> 143520
A8: 3 | B8: C3. Consent & Governance Engine (FHIR Consent, purpose-of-use, audit) | C8: Core Platform | D8: 1 | E8: 4 | F8: =Assumptions!$B$13 -> 0.65 | G8: =1-F8 -> 0.35 | H8: =$E8*Assumptions!$B$5*F8 -> 416 | I8: =$E8*Assumptions!$B$5*G8 -> 224 | J8: =H8*Assumptions!$B$9 -> 81120 | K8: =I8*Assumptions!$B$10 -> 14560 | L8: =J8+K8 -> 95680
A9: 4 | B9: C4. Agent Orchestration Engine (reasoning, workflow, guardrails) | C9: Core Platform | D9: 1 | E9: 10 | F9: =Assumptions!$B$13 -> 0.65 | G9: =1-F9 -> 0.35 | H9: =$E9*Assumptions!$B$5*F9 -> 1040 | I9: =$E9*Assumptions!$B$5*G9 -> 560 | J9: =H9*Assumptions!$B$9 -> 202800 | K9: =I9*Assumptions!$B$10 -> 36400 | L9: =J9+K9 -> 239200
A10: 5 | B10: C5. Identity, Security & Platform Ops (IAM, hosting, DevSecOps, observability) | C10: Core Platform | D10: 1 | E10: 5 | F10: =Assumptions!$B$13 -> 0.65 | G10: =1-F10 -> 0.35 | H10: =$E10*Assumptions!$B$5*F10 -> 520 | I10: =$E10*Assumptions!$B$5*G10 -> 280 | J10: =H10*Assumptions!$B$9 -> 101400 | K10: =I10*Assumptions!$B$10 -> 18200 | L10: =J10+K10 -> 119600
A11: 6 | B11: P1. Care Manager Workspace (worklist, gaps-in-care, root-cause views) | C11: Persona Module | D11: 1 | E11: 5 | F11: =Assumptions!$B$14 -> 0.45 | G11: =1-F11 -> 0.55 | H11: =$E11*Assumptions!$B$5*F11 -> 360 | I11: =$E11*Assumptions!$B$5*G11 -> 440 | J11: =H11*Assumptions!$B$9 -> 70200 | K11: =I11*Assumptions!$B$10 -> 28600 | L11: =J11+K11 -> 98800
A12: 7 | B12: P2. Case Manager / Care Coordinator Configuration (workflow variant) | C12: Persona Module | D12: 1 | E12: 1.5 | F12: =Assumptions!$B$14 -> 0.45 | G12: =1-F12 -> 0.55 | H12: =$E12*Assumptions!$B$5*F12 -> 108 | I12: =$E12*Assumptions!$B$5*G12 -> 132 | J12: =H12*Assumptions!$B$9 -> 21060 | K12: =I12*Assumptions!$B$10 -> 8580 | L12: =J12+K12 -> 29640
A13: 8 | B13: P5. Community-Based Organization (CBO) Referral & Closed-Loop Module | C13: Persona Module | D13: 1 | E13: 3 | F13: =Assumptions!$B$14 -> 0.45 | G13: =1-F13 -> 0.55 | H13: =$E13*Assumptions!$B$5*F13 -> 216 | I13: =$E13*Assumptions!$B$5*G13 -> 264 | J13: =H13*Assumptions!$B$9 -> 42120 | K13: =I13*Assumptions!$B$10 -> 17160 | L13: =J13+K13 -> 59280
A14: 9 | B14: D1. Clinical EHR FHIR Connector | C14: Data Connector | D14: 1 | E14: 3 | F14: =Assumptions!$B$15 -> 0.35 | G14: =1-F14 -> 0.65 | H14: =$E14*Assumptions!$B$5*F14 -> 168 | I14: =$E14*Assumptions!$B$5*G14 -> 312 | J14: =H14*Assumptions!$B$9 -> 32760 | K14: =I14*Assumptions!$B$10 -> 20280 | L14: =J14+K14 -> 53040
A15: 10 | B15: D2. Claims & Eligibility (X12 837/835) Connector | C15: Data Connector | D15: 1 | E15: 3 | F15: =Assumptions!$B$15 -> 0.35 | G15: =1-F15 -> 0.65 | H15: =$E15*Assumptions!$B$5*F15 -> 168 | I15: =$E15*Assumptions!$B$5*G15 -> 312 | J15: =H15*Assumptions!$B$9 -> 32760 | K15: =I15*Assumptions!$B$10 -> 20280 | L15: =J15+K15 -> 53040
A16: 11 | B16: D3. SDOH Manual Assessment Intake (PRAPARE / AHC HRSN) | C16: Data Connector | D16: 1 | E16: 2 | F16: =Assumptions!$B$15 -> 0.35 | G16: =1-F16 -> 0.65 | H16: =$E16*Assumptions!$B$5*F16 -> 112 | I16: =$E16*Assumptions!$B$5*G16 -> 208 | J16: =H16*Assumptions!$B$9 -> 21840 | K16: =I16*Assumptions!$B$10 -> 13520 | L16: =J16+K16 -> 35360
A17: 12 | B17: D5. CBO / Community Referral Network Connector | C17: Data Connector | D17: 1 | E17: 2 | F17: =Assumptions!$B$15 -> 0.35 | G17: =1-F17 -> 0.65 | H17: =$E17*Assumptions!$B$5*F17 -> 112 | I17: =$E17*Assumptions!$B$5*G17 -> 208 | J17: =H17*Assumptions!$B$9 -> 21840 | K17: =I17*Assumptions!$B$10 -> 13520 | L17: =J17+K17 -> 35360
A18: 13 | B18: P3. Provider & Specialist Module (SMART on FHIR, EHR-embedded) | C18: Persona Module | D18: 2 | E18: 4 | F18: =Assumptions!$B$14 -> 0.45 | G18: =1-F18 -> 0.55 | H18: =$E18*Assumptions!$B$5*F18 -> 288 | I18: =$E18*Assumptions!$B$5*G18 -> 352 | J18: =H18*Assumptions!$B$9 -> 56160 | K18: =I18*Assumptions!$B$10 -> 22880 | L18: =J18+K18 -> 79040
A19: 14 | B19: P4. Resident / Consumer Engagement (portal + SMS, tiered autonomy) | C19: Persona Module | D19: 2 | E19: 4 | F19: =Assumptions!$B$14 -> 0.45 | G19: =1-F19 -> 0.55 | H19: =$E19*Assumptions!$B$5*F19 -> 288 | I19: =$E19*Assumptions!$B$5*G19 -> 352 | J19: =H19*Assumptions!$B$9 -> 56160 | K19: =I19*Assumptions!$B$10 -> 22880 | L19: =J19+K19 -> 79040
A20: 15 | B20: D4. Behavioral Health + 42 CFR Part 2 Consent Connector | C20: Data Connector | D20: 2 | E20: 3 | F20: =Assumptions!$B$15 -> 0.35 | G20: =1-F20 -> 0.65 | H20: =$E20*Assumptions!$B$5*F20 -> 168 | I20: =$E20*Assumptions!$B$5*G20 -> 312 | J20: =H20*Assumptions!$B$9 -> 32760 | K20: =I20*Assumptions!$B$10 -> 20280 | L20: =J20+K20 -> 53040
A21: 16 | B21: D6. Patient Access API Connector (real-time, consent-based) | C21: Data Connector | D21: 2 | E21: 3 | F21: =Assumptions!$B$15 -> 0.35 | G21: =1-F21 -> 0.65 | H21: =$E21*Assumptions!$B$5*F21 -> 168 | I21: =$E21*Assumptions!$B$5*G21 -> 312 | J21: =H21*Assumptions!$B$9 -> 32760 | K21: =I21*Assumptions!$B$10 -> 20280 | L21: =J21+K21 -> 53040
A22: 17 | B22: D7. Provider Access API Connector (real-time) | C22: Data Connector | D22: 2 | E22: 3 | F22: =Assumptions!$B$15 -> 0.35 | G22: =1-F22 -> 0.65 | H22: =$E22*Assumptions!$B$5*F22 -> 168 | I22: =$E22*Assumptions!$B$5*G22 -> 312 | J22: =H22*Assumptions!$B$9 -> 32760 | K22: =I22*Assumptions!$B$10 -> 20280 | L22: =J22+K22 -> 53040
A23: 18 | B23: P6. County / MCO Program Administrator Analytics | C23: Persona Module | D23: 3 | E23: 5 | F23: =Assumptions!$B$14 -> 0.45 | G23: =1-F23 -> 0.55 | H23: =$E23*Assumptions!$B$5*F23 -> 360 | I23: =$E23*Assumptions!$B$5*G23 -> 440 | J23: =H23*Assumptions!$B$9 -> 70200 | K23: =I23*Assumptions!$B$10 -> 28600 | L23: =J23+K23 -> 98800
A24: 19 | B24: P7. RHTP Director Command Center (cross-program oversight & admin) | C24: Persona Module | D24: 3 | E24: 4 | F24: =Assumptions!$B$14 -> 0.45 | G24: =1-F24 -> 0.55 | H24: =$E24*Assumptions!$B$5*F24 -> 288 | I24: =$E24*Assumptions!$B$5*G24 -> 352 | J24: =H24*Assumptions!$B$9 -> 56160 | K24: =I24*Assumptions!$B$10 -> 22880 | L24: =J24+K24 -> 79040
A25: 20 | B25: P8. Value-Based Care / Contract Management Module | C25: Persona Module | D25: 3 | E25: 6 | F25: =Assumptions!$B$14 -> 0.45 | G25: =1-F25 -> 0.55 | H25: =$E25*Assumptions!$B$5*F25 -> 432 | I25: =$E25*Assumptions!$B$5*G25 -> 528 | J25: =H25*Assumptions!$B$9 -> 84240 | K25: =I25*Assumptions!$B$10 -> 34320 | L25: =J25+K25 -> 118560
A26: 21 | B26: D8. Medicaid Enterprise Data Warehouse (EDW) Connector | C26: Data Connector | D26: 3 | E26: 4 | F26: =Assumptions!$B$15 -> 0.35 | G26: =1-F26 -> 0.65 | H26: =$E26*Assumptions!$B$5*F26 -> 224 | I26: =$E26*Assumptions!$B$5*G26 -> 416 | J26: =H26*Assumptions!$B$9 -> 43680 | K26: =I26*Assumptions!$B$10 -> 27040 | L26: =J26+K26 -> 70720
A27: 22 | B27: D9. All-Payer Claims Database (APCD) Connector | C27: Data Connector | D27: 3 | E27: 4 | F27: =Assumptions!$B$15 -> 0.35 | G27: =1-F27 -> 0.65 | H27: =$E27*Assumptions!$B$5*F27 -> 224 | I27: =$E27*Assumptions!$B$5*G27 -> 416 | J27: =H27*Assumptions!$B$9 -> 43680 | K27: =I27*Assumptions!$B$10 -> 27040 | L27: =J27+K27 -> 70720
A28: 23 | B28: D10. Public Health Connector (Immunization IIS + Vital Records) | C28: Data Connector | D28: 3 | E28: 3 | F28: =Assumptions!$B$15 -> 0.35 | G28: =1-F28 -> 0.65 | H28: =$E28*Assumptions!$B$5*F28 -> 168 | I28: =$E28*Assumptions!$B$5*G28 -> 312 | J28: =H28*Assumptions!$B$9 -> 32760 | K28: =I28*Assumptions!$B$10 -> 20280 | L28: =J28+K28 -> 53040
B29: TOTAL — ALL PHASES | E29: =SUM(E6:E28) -> 95.5 | H29: =SUM(H6:H28) -> 7452 | I29: =SUM(I6:I28) -> 7828 | J29: =SUM(J6:J28) -> 1453140 | K29: =SUM(K6:K28) -> 508820 | L29: =SUM(L6:L28) -> 1961960

Sheet Phase Summary
A1: Phase Summary — Cost, Duration, and Team Size
A2: Module costs roll up automatically from the Module Build Cost sheet. Duration and Phase 0 discovery cost are inputs.
A4: Phase | B4: Description | C4: Duration (months) | D4: # Modules | E4: Total FTE-Months | F4: Total Build Cost | G4: Avg. Concurrent FTE
A5: Phase 0 | B5: Discovery & Foundation Setup (environment, security baseline, cohort selection, integration design) | C5: 1.5 | D5: n/a — fixed-scope | E5: n/a | F5: 150000 | G5: n/a
A6: Phase 1 | B6: MVP / First Value — core platform + Care Manager & CBO workflow + 4 priority connectors, one high-risk cohort | C6: 3.5 | D6: =COUNTIF('Module Build Cost'!$D$6:$D$28,1) -> 12 | E6: =SUMIFS('Module Build Cost'!$E$6:$E$28,'Module Build Cost'!$D$6:$D$28,1) -> 52.5 | F6: =SUMIFS('Module Build Cost'!$L$6:$L$28,'Module Build Cost'!$D$6:$D$28,1) -> 1153880 | G6: =E6/C6 -> 15
A7: Phase 2 | B7: Expand Reach & Real-Time — Provider & Resident modules, BH connector, Patient/Provider Access APIs | C7: 3 | D7: =COUNTIF('Module Build Cost'!$D$6:$D$28,2) -> 5 | E7: =SUMIFS('Module Build Cost'!$E$6:$E$28,'Module Build Cost'!$D$6:$D$28,2) -> 17 | F7: =SUMIFS('Module Build Cost'!$L$6:$L$28,'Module Build Cost'!$D$6:$D$28,2) -> 317200 | G7: =E7/C7 -> 5.6666667
A8: Phase 3 | B8: Program & Population Scale — county/MCO analytics, RHTP Director console, VBC module, EDW/APCD/public health | C8: 6 | D8: =COUNTIF('Module Build Cost'!$D$6:$D$28,3) -> 6 | E8: =SUMIFS('Module Build Cost'!$E$6:$E$28,'Module Build Cost'!$D$6:$D$28,3) -> 26 | F8: =SUMIFS('Module Build Cost'!$L$6:$L$28,'Module Build Cost'!$D$6:$D$28,3) -> 490880 | G8: =E8/C8 -> 4.3333333
A9: TOTAL | C9: =SUM(C5:C8) -> 14 | D9: =SUM(D6:D8) -> 23 | E9: =SUM(E6:E8) -> 95.5 | F9: =SUM(F5:F8) -> 2111960

Sheet Run & Maintain
A1: Annual Run & Maintain Cost — Steady State
A2: Steady-state support team once all phases are live, plus infrastructure and licensing. Rates link to the Rate Card sheet.
A4: Role | B4: FTE | C4: % Onshore | D4: Onshore Rate | E4: Offshore Rate | F4: Annual Hours | G4: Annual Labor Cost
A5: Platform / DevSecOps Engineer | B5: 1.5 | C5: 0.4 | D5: ='Rate Card'!$B$9 -> 190 | E5: ='Rate Card'!$C$9 -> 65 | F5: =B5*Assumptions!$B$5*Assumptions!$B$6 -> 2880 | G5: =F5*(C5*D5+(1-C5)*E5) -> 331200
A6: Data / Integration Engineer | B6: 1.5 | C6: 0.3 | D6: ='Rate Card'!$B$8 -> 185 | E6: ='Rate Card'!$C$8 -> 60 | F6: =B6*Assumptions!$B$5*Assumptions!$B$6 -> 2880 | G6: =F6*(C6*D6+(1-C6)*E6) -> 280800
A7: AI / Agent Orchestration Engineer | B7: 1 | C7: 0.6 | D7: ='Rate Card'!$B$7 -> 210 | E7: ='Rate Card'!$C$7 -> 75 | F7: =B7*Assumptions!$B$5*Assumptions!$B$6 -> 1920 | G7: =F7*(C7*D7+(1-C7)*E7) -> 299520
A8: QA / Test Engineer | B8: 0.5 | C8: 0.2 | D8: ='Rate Card'!$B$11 -> 150 | E8: ='Rate Card'!$C$11 -> 45 | F8: =B8*Assumptions!$B$5*Assumptions!$B$6 -> 960 | G8: =F8*(C8*D8+(1-C8)*E8) -> 63360
A9: Support Analyst (L1/L2) | B9: 1.5 | C9: 0.1 | D9: ='Rate Card'!$B$14 -> 130 | E9: ='Rate Card'!$C$14 -> 40 | F9: =B9*Assumptions!$B$5*Assumptions!$B$6 -> 2880 | G9: =F9*(C9*D9+(1-C9)*E9) -> 141120
A10: Engagement / Program Lead | B10: 0.5 | C10: 1 | D10: ='Rate Card'!$B$5 -> 220 | E10: ='Rate Card'!$C$5 -> 70 | F10: =B10*Assumptions!$B$5*Assumptions!$B$6 -> 960 | G10: =F10*(C10*D10+(1-C10)*E10) -> 211200
A11: Clinical / Business SME | B11: 0.25 | C11: 1 | D11: ='Rate Card'!$B$12 -> 200 | E11: n/a | F11: =B11*Assumptions!$B$5*Assumptions!$B$6 -> 480 | G11: =F11*(C11*D11) -> 96000
A12: Subtotal — Steady-State Labor | G12: =SUM(G5:G11) -> 1423200
A14: Infrastructure, Cloud & Licensing
A15: Item | B15: Annual Cost | C15: Note
A16: Cloud hosting & compute (incl. agent/LLM inference) | B16: 600000 | C16: $50K/month placeholder — replace with real workload sizing
A17: FHIR server, knowledge graph DB & integration middleware licensing | B17: 180000 | C17: Illustrative annual license/subscription placeholder
A18: Monitoring, security & observability tooling | B18: 70000 | C18: Illustrative annual placeholder
A19: Subtotal — Infrastructure & Licensing | B19: =SUM(B16:B18) -> 850000
A21: TOTAL ANNUAL RUN COST — STEADY STATE | B21: =G12+B19 -> 2273200
A23: Phase 1 pilot ramp — % of steady-state run cost | B23: 0.4 | C23: Smaller team, one cohort, fewer connectors live during Phase 1
A24: Phase 1 partial-year run cost | B24: =B21*B23 -> 909280

Sheet ROI Illustration
A1: Phase 1 ROI Illustration — Worked Example
A2: A methodology, not a projection: shows how Phase 1 investment could be weighed against avoided-utilization savings for a defined pilot cohort. Replace every blue input with the target program's real baseline data.
A4: Input | B4: Value | C4: Note
A5: Pilot cohort size (members) | B5: 7500 | C5: Illustrative high-risk / high-SDOH-need cohort within the reference deployment
A6: Baseline avoidable ED visits per member per year | B6: 0.35 | C6: Illustrative literature-informed placeholder — replace with the program's real baseline
A7: Average avoidable cost per ED visit ($) | B7: 1800 | C7: Illustrative placeholder
A8: Target reduction in avoidable utilization | B8: 0.1 | C8: Illustrative, directional — needs validation against comparable care-coordination programs
A10: Calculated | B10: Value | C10: Formula logic
A11: Baseline avoidable ED visits (cohort) | B11: =B5*B6 -> 2625 | C11: Cohort size × baseline rate
A12: Avoided visits at target reduction | B12: =B11*B8 -> 262.5 | C12: Baseline visits × target reduction %
A13: Gross annual avoided-cost savings | B13: =B12*B7 -> 472500 | C13: Avoided visits × avg cost per visit
A15: Phase 1 build cost (link) | B15: ='Phase Summary'!$F$6 -> 1153880 | C15: From Phase Summary
A16: Phase 1 partial-year run cost (link) | B16: ='Run & Maintain'!$B$24 -> 909280 | C16: From Run & Maintain
A17: Total Phase 1 investment | B17: =B15+B16 -> 2063160 | C17: Build + partial-year run
A18: Simple payback (years, illustrative) | B18: =IF(B13=0,"n/a",B17/B13) -> 4.3664762 | C18: Phase 1 investment ÷ gross annual savings
A20: At full population scale (illustrative)
A21: Population scale factor at full rollout (× pilot cohort) | B21: 4 | C21: E.g., pilot cohort expands from ~7,500 to ~30,000 high-risk members across the full reference population
A22: Full-scale gross annual avoided-cost savings | B22: =B13*B21 -> 1890000 | C22: Phase 1 pilot savings × scale factor
A23: Total platform investment (build, all phases + Phase 0) | B23: ='Phase Summary'!$F$9 -> 2111960 | C23: From Phase Summary total
A24: Plus one year steady-state run cost | B24: ='Run & Maintain'!$B$21 -> 2273200 | C24: From Run & Maintain total
A25: Total investment through Year 1 at full scale | B25: =B23+B24 -> 4385160 | C25: Build (all phases) + one year of run
A26: Simple payback at full scale (years, illustrative) | B26: =IF(B22=0,"n/a",B25/B22) -> 2.3201905 | C26: Full-scale investment ÷ full-scale annual savings
A28: This is a directional planning tool, not a savings guarantee. Validate baseline utilization, avoidable-cost, and expected-reduction assumptions against the target program's actual claims history before using these numbers externally.

Sheet Timeline
A1: Delivery Timeline (Months from Kickoff)
A2: Feeds the roadmap graphic in the companion Word document. Durations link to Phase Summary.
A4: Phase | B4: Description | C4: Start Month | D4: Duration (months) | E4: End Month
A5: Phase 0 | B5: ='Phase Summary'!B5 -> Discovery & Foundation Setup (environment, security baseline, cohort selection, integration design) | C5: 0 | D5: ='Phase Summary'!C5 -> 1.5 | E5: =C5+D5 -> 1.5
A6: Phase 1 | B6: ='Phase Summary'!B6 -> MVP / First Value — core platform + Care Manager & CBO workflow + 4 priority connectors, one high-risk cohort | C6: =E5 -> 1.5 | D6: ='Phase Summary'!C6 -> 3.5 | E6: =C6+D6 -> 5
A7: Phase 2 | B7: ='Phase Summary'!B7 -> Expand Reach & Real-Time — Provider & Resident modules, BH connector, Patient/Provider Access APIs | C7: =E6 -> 5 | D7: ='Phase Summary'!C7 -> 3 | E7: =C7+D7 -> 8
A8: Phase 3 | B8: ='Phase Summary'!B8 -> Program & Population Scale — county/MCO analytics, RHTP Director console, VBC module, EDW/APCD/public health | C8: =E7 -> 8 | D8: ='Phase Summary'!C8 -> 6 | E8: =C8+D8 -> 14
A10: First meaningful ROI signal targeted during Phase 1 / early Phase 2 (approx. months 5–9) — well before full Phase 3 population scale.

Sheet Approach B - Partner Model
A1: Approach B — Consulting Asset + Ecosystem Partner Model
A2: Same 23 modules. “Partner leverage %” estimates the effort avoided by integrating an established partner platform (e.g., Unite Us for CBO/community referral, an Infor Cloverleaf-class integration engine for clinical/claims interfaces) via time-boxed “connect-a-thon” sprints instead of custom-building. Core IP modules (knowledge graph, agent orchestration) keep low leverage on purpose — that's what stays IBM-differentiated.
A5: # | B5: Module | C5: Category | D5: Phase | E5: Approach A FTE-Months | F5: Partner Leverage % | G5: Approach B FTE-Months | H5: Approach A Cost | I5: Approach B Cost
A6: 1 | B6: C1. FHIR-Native Integration & Ingestion Layer (real-time API gateway + batch ETL / Bulk Data) | C6: Core Platform | D6: 1 | E6: ='Module Build Cost'!E6 -> 8 | F6: 0.35 | G6: =E6*(1-F6) -> 5.2 | H6: ='Module Build Cost'!L6 -> 191360 | I6: =H6*(1-F6) -> 124384
A7: 2 | B7: C2. Knowledge Graph & Master Person Index | C7: Core Platform | D7: 1 | E7: ='Module Build Cost'!E7 -> 6 | F7: 0.05 | G7: =E7*(1-F7) -> 5.7 | H7: ='Module Build Cost'!L7 -> 143520 | I7: =H7*(1-F7) -> 136344
A8: 3 | B8: C3. Consent & Governance Engine (FHIR Consent, purpose-of-use, audit) | C8: Core Platform | D8: 1 | E8: ='Module Build Cost'!E8 -> 4 | F8: 0.1 | G8: =E8*(1-F8) -> 3.6 | H8: ='Module Build Cost'!L8 -> 95680 | I8: =H8*(1-F8) -> 86112
A9: 4 | B9: C4. Agent Orchestration Engine (reasoning, workflow, guardrails) | C9: Core Platform | D9: 1 | E9: ='Module Build Cost'!E9 -> 10 | F9: 0.05 | G9: =E9*(1-F9) -> 9.5 | H9: ='Module Build Cost'!L9 -> 239200 | I9: =H9*(1-F9) -> 227240
A10: 5 | B10: C5. Identity, Security & Platform Ops (IAM, hosting, DevSecOps, observability) | C10: Core Platform | D10: 1 | E10: ='Module Build Cost'!E10 -> 5 | F10: 0.25 | G10: =E10*(1-F10) -> 3.75 | H10: ='Module Build Cost'!L10 -> 119600 | I10: =H10*(1-F10) -> 89700
A11: 6 | B11: P1. Care Manager Workspace (worklist, gaps-in-care, root-cause views) | C11: Persona Module | D11: 1 | E11: ='Module Build Cost'!E11 -> 5 | F11: 0.1 | G11: =E11*(1-F11) -> 4.5 | H11: ='Module Build Cost'!L11 -> 98800 | I11: =H11*(1-F11) -> 88920
A12: 7 | B12: P2. Case Manager / Care Coordinator Configuration (workflow variant) | C12: Persona Module | D12: 1 | E12: ='Module Build Cost'!E12 -> 1.5 | F12: 0.1 | G12: =E12*(1-F12) -> 1.35 | H12: ='Module Build Cost'!L12 -> 29640 | I12: =H12*(1-F12) -> 26676
A13: 8 | B13: P5. Community-Based Organization (CBO) Referral & Closed-Loop Module | C13: Persona Module | D13: 1 | E13: ='Module Build Cost'!E13 -> 3 | F13: 0.65 | G13: =E13*(1-F13) -> 1.05 | H13: ='Module Build Cost'!L13 -> 59280 | I13: =H13*(1-F13) -> 20748
A14: 9 | B14: D1. Clinical EHR FHIR Connector | C14: Data Connector | D14: 1 | E14: ='Module Build Cost'!E14 -> 3 | F14: 0.45 | G14: =E14*(1-F14) -> 1.65 | H14: ='Module Build Cost'!L14 -> 53040 | I14: =H14*(1-F14) -> 29172
A15: 10 | B15: D2. Claims & Eligibility (X12 837/835) Connector | C15: Data Connector | D15: 1 | E15: ='Module Build Cost'!E15 -> 3 | F15: 0.4 | G15: =E15*(1-F15) -> 1.8 | H15: ='Module Build Cost'!L15 -> 53040 | I15: =H15*(1-F15) -> 31824
A16: 11 | B16: D3. SDOH Manual Assessment Intake (PRAPARE / AHC HRSN) | C16: Data Connector | D16: 1 | E16: ='Module Build Cost'!E16 -> 2 | F16: 0.1 | G16: =E16*(1-F16) -> 1.8 | H16: ='Module Build Cost'!L16 -> 35360 | I16: =H16*(1-F16) -> 31824
A17: 12 | B17: D5. CBO / Community Referral Network Connector | C17: Data Connector | D17: 1 | E17: ='Module Build Cost'!E17 -> 2 | F17: 0.7 | G17: =E17*(1-F17) -> 0.6 | H17: ='Module Build Cost'!L17 -> 35360 | I17: =H17*(1-F17) -> 10608
... A28: 23 | B28: D10. Public Health Connector (Immunization IIS + Vital Records) | C28: Data Connector | D28: 3 | E28: ='Module Build Cost'!E28 -> 3 | F28: 0.25 | G28: =E28*(1-F28) -> 2.25 | H28: ='Module Build Cost'!L28 -> 53040 | I28: =H28*(1-F28) -> 39780
B29: TOTAL — ALL PHASES | E29: =SUM(E6:E28) -> 95.5 | G29: =SUM(G6:G28) -> 75.55 | H29: =SUM(H6:H28) -> 1961960 | I29: =SUM(I6:I28) -> 1564732
A32: Phase rollup — Approach B
A33: Phase | B33: Approach A Cost | C33: Approach B Cost | D33: $ Reduction | E33: % Reduction
A34: Phase 1 | B34: =SUMIFS($H$6:$H$28,$D$6:$D$28,1) -> 1153880 | C34: =SUMIFS($I$6:$I$28,$D$6:$D$28,1) -> 903552 | D34: =B34-C34 -> 250328 | E34: =IFERROR(D34/B34,0) -> 0.21694457
A35: Phase 2 | B35: =SUMIFS($H$6:$H$28,$D$6:$D$28,2) -> 317200 | C35: =SUMIFS($I$6:$I$28,$D$6:$D$28,2) -> 252356 | D35: =B35-C35 -> 64844 | E35: =IFERROR(D35/B35,0) -> 0.20442623
A36: Phase 3 | B36: =SUMIFS($H$6:$H$28,$D$6:$D$28,3) -> 490880 | C36: =SUMIFS($I$6:$I$28,$D$6:$D$28,3) -> 408824 | D36: =B36-C36 -> 82056 | E36: =IFERROR(D36/B36,0) -> 0.16716102
A38: IBM asset investment vs. first-client incremental cost
A39: The reusable IP asset — funded by IBM once, before any client is signed — covers the core platform plus the four most universal Phase 1 connectors and a generic reference Care Manager workspace. Client-specific configuration (case-manager variant, CBO/Unite Us tenant setup, Phase 0 discovery, Phases 2–3) is priced per engagement.
A40: Item | B40: Approach B Cost
A41: IBM asset build (Core Platform + P1 + D1/D2/D3/D5) | B41: =$I$6+$I$7+$I$8+$I$9+$I$10+$I$11+$I$14+$I$15+$I$16+$I$17 -> 856128
A42: First-client Phase 1 configuration (P2 case-manager variant + P5 Unite Us tenant setup) | B42: =$I$12+$I$13 -> 47424
A43: First-client Phase 0 discovery (reduced — partner onboarding playbook already exists) | B43: 110000
A44: First client — total incremental cost to MVP (on top of the asset) | B44: =B42+B43 -> 157424
A46: Approach B — Run & Maintain (Steady State)
A47: Item | B47: Approach B Annual Cost
A48: Support labor (reduced — fewer bespoke connectors to maintain) | B48: ='Run & Maintain'!$G$12*0.85 -> 1209720
A49: Cloud hosting & compute | B49: ='Run & Maintain'!$B$16*0.9 -> 540000
A50: IBM-built licensing & tooling (reduced scope) | B50: ='Run & Maintain'!$B$17*0.5 -> 90000
A51: Monitoring, security & observability | B51: ='Run & Maintain'!$B$18 -> 70000
A52: Partner platform fees (Unite Us network access + Cloverleaf-class engine licensing) | B52: 150000
A53: TOTAL — Approach B Steady State | B53: =SUM(B48:B52) -> 2059720
A55: Phase 1 pilot ramp — % of steady-state run cost | B55: ='Run & Maintain'!$B$23 -> 0.4
A56: First client Phase 1 partial-year run cost | B56: =B53*B55 -> 823888

Sheet A vs B Comparison
A1: Approach A vs. Approach B — Side-by-Side
A2: Approach A: full custom build. Approach B: reusable IBM IP asset + ecosystem partner connectors (Unite Us, Infor Cloverleaf-class integration engine) via connect-a-thon sprints. All figures link to the sheets above.
A4: Metric | B4: Approach A (Full Custom Build) | C4: Approach B (Asset + Partners) | D4: Difference
A5: Total build cost, all phases | B5: ='Phase Summary'!F9 -> 2111960 | C5: ='Approach B - Partner Model'!I29+'Approach B - Partner Model'!B43 -> 1674732 | D5: =B5-C5 -> 437228
A6: Phase 0 + Phase 1 / MVP build cost | B6: ='Phase Summary'!F6+'Phase Summary'!F5 -> 1303880 | C6: ='Approach B - Partner Model'!C34+'Approach B - Partner Model'!B43 -> 1013552 | D6: =B6-C6 -> 290328
A7: IBM upfront asset investment (pre-client) | B7: n/a — not applicable | C7: ='Approach B - Partner Model'!B41 -> 856128 | D7: n/a
A8: First client's incremental cost to MVP (on top of the asset) | B8: ='Phase Summary'!F6 -> 1153880 | C8: ='Approach B - Partner Model'!B44 -> 157424 | D8: =B8-C8 -> 996456
A9: Total duration, all phases (months) | B9: ='Phase Summary'!C9 -> 14 | C9: 10.5 | D9: =B9-C9 -> 3.5
A10: Time to first live functionality (months) | B10: =Timeline!E6 -> 5 | C10: 3.75 | D10: =B10-C10 -> 1.25
A11: Annual run cost, steady state | B11: ='Run & Maintain'!B21 -> 2273200 | C11: ='Approach B - Partner Model'!B53 -> 2059720 | D11: =B11-C11 -> 213480
A13: ROI comparison (same pilot-cohort assumptions as the ROI Illustration tab)
A14: Metric | B14: Approach A | C14: Approach B
A15: Gross annual avoided-cost savings (pilot cohort) | B15: ='ROI Illustration'!B13 -> 472500 | C15: ='ROI Illustration'!B13 -> 472500
A16: Total Phase 1 investment (asset + first client, build + run ramp) | B16: ='ROI Illustration'!B17 -> 2063160 | C16: ='Approach B - Partner Model'!B41+'Approach B - Partner Model'!B44+'Approach B - Partner Model'!B56 -> 1837440
A17: — of which, first client's own incremental cash cost | B17: n/a | C17: ='Approach B - Partner Model'!B44+'Approach B - Partner Model'!B56 -> 981312
A18: Simple payback — full investment basis (years) | B18: ='ROI Illustration'!B18 -> 4.3664762 | C18: =C16/C15 -> 3.8887619
A19: Simple payback — first client's own cash cost only (years) | B19: n/a — asset not separated under Approach A | C19: =C17/C15 -> 2.0768508
A21: Key trade-off: Approach B trades some IBM-owned IP and margin on the CBO/community-referral and interoperability-engine layers for materially lower upfront cost, a faster timeline, and a much lower bar for the first client to say yes. It also introduces partner dependency (roadmap, commercial terms, data-sharing agreements with Unite Us and the integration-engine vendor) as a new risk to manage.

Sheet Module Specification
A1: RHTP Module Specification — Screens, Inputs, Outputs
A2: All 23 modules defined across the cost model and strategy documents (5 Core Platform + 8 Persona + 10 Data Connector). Most Core Platform and Data Connector modules are backend services with no dedicated screen of their own — they surface through the persona screens and an admin/platform console noted below. Two hour-estimate columns have been added: approximate hours for a traditional human development team (linked from the Module Build Cost tab) and approximate hours using Claude ("Bob") as an AI-assisted developer, based on editable acceleration assumptions on the Assumptions tab. Both are illustrative planning estimates, not delivery commitments.
A5: # | B5: Module | C5: Category | D5: Phase | E5: Associated Screen / View | F5: Key Inputs | G5: Key Outputs | H5: Dev Team Development Hours | I5: Bob (Claude) Dev Hours
A6: 1 | B6: C1. FHIR-Native Integration & Ingestion Layer | C6: Core Platform | D6: 1 | E6: Admin Console — Data Source Connection Status | F6: Raw source feeds: EHR FHIR APIs, X12 837/835 claims files, batch extracts, real-time API calls (Patient/Provider Access, IIS) | G6: Normalized FHIR R4 resources published to the knowledge graph ingestion queue; connection health/status events | H6: ='Module Build Cost'!H6+'Module Build Cost'!I6 -> 1280 | I6: =ROUND(H6*IF(C6="Core Platform",Assumptions!$B$18,IF(C6="Persona Module",Assumptions!$B$19,Assumptions!$B$20)),0) -> 640
A7: 2 | B7: C2. Knowledge Graph & Master Person Index | C7: Core Platform | D7: 1 | E7: Backend — surfaces as the “360 Person View” panel embedded in every persona screen | F7: Normalized FHIR resources from all connectors; entity records needing identity resolution | G7: Resolved master person record; relationship graph (person–caregiver–provider–CBO–program); queryable API for every other module | H7: ='Module Build Cost'!H7+'Module Build Cost'!I7 -> 960 | I7: =ROUND(H7*IF(C7="Core Platform",Assumptions!$B$18,IF(C7="Persona Module",Assumptions!$B$19,Assumptions!$B$20)),0) -> 480
A8: 3 | B8: C3. Consent & Governance Engine | C8: Core Platform | D8: 1 | E8: Consent Management screen (resident-facing) + Admin Console (governance view) | F8: Consent capture events, purpose-of-use tags, program/legal data-sharing agreements | G8: FHIR Consent resources; allow/deny access decisions enforced at query time; audit log entries | H8: ='Module Build Cost'!H8+'Module Build Cost'!I8 -> 640 | I8: =ROUND(H8*IF(C8="Core Platform",Assumptions!$B$18,IF(C8="Persona Module",Assumptions!$B$19,Assumptions!$B$20)),0) -> 320
A9: 4 | B9: C4. Agent Orchestration Engine | C9: Core Platform | D9: 1 | E9: Backend — surfaces as the “Recommended Actions / Agent Activity” panel on persona dashboards | F9: Knowledge graph state, gap/risk signals, persona workflow rules, governance guardrails from C3 | G9: Recommended actions, auto-generated tasks/referrals, routed notifications, action audit trail | H9: ='Module Build Cost'!H9+'Module Build Cost'!I9 -> 1600 | I9: =ROUND(H9*IF(C9="Core Platform",Assumptions!$B$18,IF(C9="Persona Module",Assumptions!$B$19,Assumptions!$B$20)),0) -> 800
A10: 5 | B10: C5. Identity, Security & Platform Ops | C10: Core Platform | D10: 1 | E10: Admin Console — Platform Administration screen | F10: User directory, role definitions, security events, deployment artifacts, telemetry | G10: Authenticated sessions, role-based access tokens, uptime/observability dashboards, CI/CD deployments | H10: ='Module Build Cost'!H10+'Module Build Cost'!I10 -> 800 | I10: =ROUND(H10*IF(C10="Core Platform",Assumptions!$B$18,IF(C10="Persona Module",Assumptions!$B$19,Assumptions!$B$20)),0) -> 400
A11: 6 | B11: P1. Care Manager Workspace | C11: Persona Module | D11: 1 | E11: Care Manager Dashboard / Worklist screen | F11: Person records and relationships (C2), gap-in-care flags, agent recommendations (C4) | G11: Prioritized worklist, updated care plan, tasks/referrals assigned to other stakeholders | H11: ='Module Build Cost'!H11+'Module Build Cost'!I11 -> 800 | I11: =ROUND(H11*IF(C11="Core Platform",Assumptions!$B$18,IF(C11="Persona Module",Assumptions!$B$19,Assumptions!$B$20)),0) -> 240
A12: 7 | B12: P2. Case Manager / Care Coordinator Configuration | C12: Persona Module | D12: 1 | E12: Case Manager Worklist screen (workflow variant of P1) | F12: Same as P1, filtered/configured for social-services and benefits workflow | G12: Case notes, service plan updates, benefit-program task assignments | H12: ='Module Build Cost'!H12+'Module Build Cost'!I12 -> 240 | I12: =ROUND(H12*IF(C12="Core Platform",Assumptions!$B$18,IF(C12="Persona Module",Assumptions!$B$19,Assumptions!$B$20)),0) -> 72
A13: 8 | B13: P5. CBO Referral & Closed-Loop Module | C13: Persona Module | D13: 1 | E13: CBO Referral Inbox screen | F13: Referral requests generated by care manager or agent orchestration | G13: Referral acceptance/decline, service-delivery confirmation, closed-loop status back to the knowledge graph | H13: ='Module Build Cost'!H13+'Module Build Cost'!I13 -> 480 | I13: =ROUND(H13*IF(C13="Core Platform",Assumptions!$B$18,IF(C13="Persona Module",Assumptions!$B$19,Assumptions!$B$20)),0) -> 144
A14: 9 | B14: D1. Clinical EHR FHIR Connector | C14: Data Connector | D14: 1 | E14: Backend — status shown in Admin Console | F14: EHR FHIR API feed (Patient, Condition, Observation, MedicationRequest, CarePlan) | G14: Normalized clinical FHIR resources into C1/C2 | H14: ='Module Build Cost'!H14+'Module Build Cost'!I14 -> 480 | I14: =ROUND(H14*IF(C14="Core Platform",Assumptions!$B$18,IF(C14="Persona Module",Assumptions!$B$19,Assumptions!$B$20)),0) -> 168
A15: 10 | B15: D2. Claims & Eligibility (X12 837/835) Connector | C15: Data Connector | D15: 1 | E15: Backend — status shown in Admin Console | F15: X12 837/835 claims and eligibility files | G15: Normalized claims/eligibility FHIR resources into C1/C2 | H15: ='Module Build Cost'!H15+'Module Build Cost'!I15 -> 480 | I15: =ROUND(H15*IF(C15="Core Platform",Assumptions!$B$18,IF(C15="Persona Module",Assumptions!$B$19,Assumptions!$B$20)),0) -> 168
A16: 11 | B16: D3. SDOH Manual Assessment Intake | C16: Data Connector | D16: 1 | E16: SDOH Assessment Entry Form (used by Care Manager and CBO screens) | F16: PRAPARE / AHC HRSN screening responses entered by care coordinators or CBOs | G16: Structured SDOH observations into the knowledge graph | H16: ='Module Build Cost'!H16+'Module Build Cost'!I16 -> 320 | I16: =ROUND(H16*IF(C16="Core Platform",Assumptions!$B$18,IF(C16="Persona Module",Assumptions!$B$19,Assumptions!$B$20)),0) -> 112
A17: 12 | B17: D5. CBO / Community Referral Network Connector | C17: Data Connector | D17: 1 | E17: Backend — feeds the P5 CBO Referral Inbox screen | F17: CBO network referral and status-update API calls | G17: Referral, Task, and ServiceRequest resources into the knowledge graph | H17: ='Module Build Cost'!H17+'Module Build Cost'!I17 -> 320 | I17: =ROUND(H17*IF(C17="Core Platform",Assumptions!$B$18,IF(C17="Persona Module",Assumptions!$B$19,Assumptions!$B$20)),0) -> 112
... A28: 23 | B28: D10. Public Health Connector (Immunization IIS + Vital Records) | C28: Data Connector | D28: 3 | E28: Backend — status shown in Admin Console | F28: State/local IIS query responses; vital records batch feed | G28: Immunization and vital-status resources into C1/C2 | H28: ='Module Build Cost'!H28+'Module Build Cost'!I28 -> 480 | I28: =ROUND(H28*IF(C28="Core Platform",Assumptions!$B$18,IF(C28="Persona Module",Assumptions!$B$19,Assumptions!$B$20)),0) -> 168
B29: TOTAL — ALL MODULES | H29: =SUM(H6:H28) -> 15280 | I29: =SUM(I6:I28) -> 5880
